{"format_version":"1.12.0","minecraft:geometry":[{"description":{"identifier":"geometry.zygarde_100","texture_width":256,"texture_height":256,"visible_bounds_width":10,"visible_bounds_height":6.5,"visible_bounds_offset":[0,2.75,0]},"bones":[{"name":"zygarde","pivot":[0,0,0]},{"name":"body","parent":"zygarde","pivot":[0,33,7]},{"name":"right_leg","parent":"body","pivot":[-6.04904,33.95096,1],"rotation":[-7.4194,2.85016,-2.29678],"cubes":[{"origin":[-14,22,-5],"size":[9,11,12],"pivot":[-8,24.5,0.5],"rotation":[0,0,30],"uv":[104,88],"mirror":true},{"origin":[-9.19615,32.66025,-5],"size":[0,7,12],"pivot":[-8.19615,36.16025,1],"rotation":[0,0,10],"uv":[102,129],"mirror":true},{"origin":[-13,15,-4],"size":[7,7,10],"pivot":[-8,24.5,0.5],"rotation":[0,0,30],"uv":[134,54],"mirror":true}]},{"name":"bone10","parent":"right_leg","pivot":[-13.59968,17.89316,-0.98784],"rotation":[4.99527,-0.21782,2.4905],"cubes":[{"origin":[-18,0.14809,-4.69273],"size":[9,12,11],"uv":[110,0],"mirror":true},{"origin":[-18.29904,-0.00255,-10.19273],"size":[9,5,6],"inflate":-0.1,"uv":[144,32],"mirror":true},{"origin":[-17.29904,-0.60255,-13.19273],"size":[7,5,5],"inflate":-0.1,"pivot":[-13.79904,2.49745,-7.19273],"rotation":[-15,0,0],"uv":[146,117],"mirror":true},{"origin":[-17.29904,0.97081,-13.14358],"size":[7,7,0],"pivot":[-13.79904,3.47081,-13.14358],"rotation":[-15,0,0],"uv":[152,43],"mirror":true},{"origin":[-17,12.14809,-3.69273],"size":[7,6,9],"uv":[138,102],"mirror":true},{"origin":[-17,14.14809,-3.69273],"size":[7,8,0],"pivot":[-13.5,14.14809,-3.69273],"rotation":[12.5,0,0],"uv":[154,127],"mirror":true}]},{"name":"left_leg","parent":"body","pivot":[6.04904,33.95096,1],"rotation":[-7.4194,-2.85016,2.29678],"cubes":[{"origin":[5,22,-5],"size":[9,11,12],"pivot":[8,24.5,0.5],"rotation":[0,0,-30],"uv":[104,88]},{"origin":[9.19615,32.66025,-5],"size":[0,7,12],"pivot":[8.19615,36.16025,1],"rotation":[0,0,-10],"uv":[102,129]},{"origin":[6,15,-4],"size":[7,7,10],"pivot":[8,24.5,0.5],"rotation":[0,0,-30],"uv":[134,54]}]},{"name":"bone9","parent":"left_leg","pivot":[13.59968,17.89316,-0.98784],"rotation":[4.99527,0.21782,-2.4905],"cubes":[{"origin":[9,0.14809,-4.69273],"size":[9,12,11],"uv":[110,0]},{"origin":[9.29904,-0.00255,-10.19273],"size":[9,5,6],"inflate":-0.1,"uv":[144,32]},{"origin":[10.29904,-0.60255,-13.19273],"size":[7,5,5],"inflate":-0.1,"pivot":[13.79904,2.49745,-7.19273],"rotation":[-15,0,0],"uv":[146,117]},{"origin":[10.29904,0.97081,-13.14358],"size":[7,7,0],"pivot":[13.79904,3.47081,-13.14358],"rotation":[-15,0,0],"uv":[152,43]},{"origin":[10,12.14809,-3.69273],"size":[7,6,9],"uv":[138,102]},{"origin":[10,14.14809,-3.69273],"size":[7,8,0],"pivot":[13.5,14.14809,-3.69273],"rotation":[12.5,0,0],"uv":[154,127]}]},{"name":"main_body","parent":"body","pivot":[0,31,1],"cubes":[{"origin":[-8,30,-4],"size":[16,22,10],"uv":[0,76]}]},{"name":"chest","parent":"main_body","pivot":[0,33,7],"cubes":[{"origin":[-14,46.89624,-0.3143],"size":[28,14,13],"pivot":[0,58.89624,6.1857],"rotation":[-65,0,0],"uv":[0,0]},{"origin":[-6,55.1273,-7.80416],"size":[0,14,13],"pivot":[-7,63.1273,-1.30416],"rotation":[-36.69995,-26.94622,-13.71217],"uv":[104,114]},{"origin":[6,55.1273,-7.80416],"size":[0,14,13],"pivot":[7,63.1273,-1.30416],"rotation":[-36.69995,26.94622,13.71217],"uv":[40,108]}]},{"name":"head","parent":"chest","pivot":[0,59.89624,6.1857],"cubes":[{"origin":[-3,61.89624,-2.3143],"size":[6,8,9],"uv":[36,135]},{"origin":[-2.3,63.72124,-2.3393],"size":[1,3,0],"pivot":[-2,64.94624,-2.3393],"rotation":[0,0,-5],"uv":[82,24]},{"origin":[1.3,63.72124,-2.3393],"size":[1,3,0],"pivot":[2,64.94624,-2.3393],"rotation":[0,0,5],"uv":[82,24],"mirror":true},{"origin":[-1.075,63.44624,-2.3393],"size":[1,3,0],"uv":[8,79]},{"origin":[0.075,63.44624,-2.3393],"size":[1,3,0],"uv":[8,79],"mirror":true},{"origin":[-3,69.89624,0.6857],"size":[0,4,3],"pivot":[-3,69.89624,2.1857],"rotation":[0,0,-12.5],"uv":[46,77]},{"origin":[3,69.89624,0.6857],"size":[0,4,3],"pivot":[3,69.89624,2.1857],"rotation":[0,0,12.5],"uv":[46,73]},{"origin":[3.53708,61.16727,-3.0643],"size":[0,14,3],"pivot":[4.03708,68.16727,-1.5643],"rotation":[-6.31274,31.94715,3.19132],"uv":[0,152]},{"origin":[5.53708,61.16727,4.0643],"size":[0,14,3],"pivot":[4.03708,68.16727,1.5643],"rotation":[6.31274,-31.94715,3.19132],"uv":[0,152]},{"origin":[-5.53708,61.16727,4.0643],"size":[0,14,3],"pivot":[-4.03708,68.16727,1.5643],"rotation":[6.31274,31.94715,-3.19132],"uv":[0,152],"mirror":true},{"origin":[-3.53708,61.16727,-3.0643],"size":[0,14,3],"pivot":[-4.03708,68.16727,-1.5643],"rotation":[-6.31274,-31.94715,-3.19132],"uv":[150,151]},{"origin":[-3,69.89624,-1.8643],"size":[6,4,0],"pivot":[0,71.89624,-2.3143],"rotation":[-10,0,0],"uv":[0,9]},{"origin":[-0.5,69.39624,-2.3643],"size":[1,2,0],"uv":[198,81]},{"origin":[-0.5,71.77124,-1.8643],"size":[1,2,0],"pivot":[0,72.39624,-2.3643],"rotation":[-12.5,0,0],"uv":[209,83]},{"origin":[-3,69.89624,6.1357],"size":[6,3,0],"pivot":[0,70.39624,6.1357],"rotation":[-15,0,0],"uv":[69,8]}]},{"name":"left_eye","parent":"head","pivot":[1,66.79624,-2.4143],"rotation":[0,0,-25],"cubes":[{"origin":[0.5,65.79624,-2.4143],"size":[2,2,0],"uv":[73,11]}]},{"name":"right_eye","parent":"head","pivot":[-1,66.79624,-2.4143],"rotation":[0,0,25],"cubes":[{"origin":[-2.5,65.79624,-2.4143],"size":[2,2,0],"uv":[69,11]}]},{"name":"left_front","parent":"chest","pivot":[14,60.89624,2.1857],"rotation":[-9.72039,46.46678,7.33019],"cubes":[{"origin":[14,60.89624,-2.3143],"size":[0,24,9],"uv":[84,124]}]},{"name":"bone5","parent":"left_front","pivot":[14,84.89624,2.1857],"rotation":[0,0,-27.5],"cubes":[{"origin":[14,35.89624,-4.3143],"size":[0,49,13],"uv":[26,14]}]},{"name":"left_head","parent":"bone5","pivot":[14,35.89624,2.1857],"rotation":[0,0,-32.5],"cubes":[{"origin":[14,24.89624,-2.3143],"size":[0,11,9],"uv":[36,143]}]},{"name":"left_back","parent":"chest","pivot":[13,60.89624,6.8143],"rotation":[22.59303,-81.28015,-35.35551],"cubes":[{"origin":[13,60.89624,2.3143],"size":[0,24,9],"uv":[84,124]}]},{"name":"bone7","parent":"left_back","pivot":[13,83.89624,6.8143],"rotation":[0,0,-27.5],"cubes":[{"origin":[13.16986,66.89709,0.3143],"size":[0,17,13],"uv":[26,14]}]},{"name":"bone8","parent":"bone7","pivot":[13.16986,66.89709,6.8143],"rotation":[0,0,22.5],"cubes":[{"origin":[13.16986,17.89709,0.3143],"size":[0,49,13],"uv":[26,14]}]},{"name":"left_head2","parent":"bone8","pivot":[13.16986,17.89709,6.8143],"rotation":[0,0,-32.5],"cubes":[{"origin":[13.16986,6.89709,2.3143],"size":[0,11,9],"uv":[36,143]}]},{"name":"tail","parent":"chest","pivot":[0,50.88577,7.29411],"rotation":[0,-90,0],"cubes":[{"origin":[-0.47981,8.89624,2.79411],"size":[0,24,9],"pivot":[-0.47981,31.89624,7.29411],"rotation":[0,0,-177.5],"uv":[84,124]}]},{"name":"bone14","parent":"tail","pivot":[-0.47981,30.89624,7.29411],"rotation":[0,0,-30],"cubes":[{"origin":[-0.55161,14.77189,0.79411],"size":[0,17,13],"uv":[26,14]}]},{"name":"bone15","parent":"bone14","pivot":[-0.55161,14.77189,7.29411],"rotation":[0,0,-77.5],"cubes":[{"origin":[-0.55161,-34.22811,0.79411],"size":[0,49,13],"uv":[78,159]}]},{"name":"left_head3","parent":"bone15","pivot":[-0.55161,-34.22811,7.29411],"rotation":[0,0,-40],"cubes":[{"origin":[-0.55161,-45.22811,2.79411],"size":[0,11,9],"uv":[36,167]}]},{"name":"right_back","parent":"chest","pivot":[-13,60.89624,6.8143],"rotation":[22.59303,81.28015,35.35551],"cubes":[{"origin":[-13,60.89624,2.3143],"size":[0,24,9],"uv":[84,124],"mirror":true}]},{"name":"bone11","parent":"right_back","pivot":[-13,83.89624,6.8143],"rotation":[0,0,27.5],"cubes":[{"origin":[-13.16986,66.89709,0.3143],"size":[0,17,13],"uv":[26,14],"mirror":true}]},{"name":"bone12","parent":"bone11","pivot":[-13.16986,66.89709,6.8143],"rotation":[0,0,-22.5],"cubes":[{"origin":[-13.16986,17.89709,0.3143],"size":[0,49,13],"uv":[0,156],"mirror":true}]},{"name":"right_head2","parent":"bone12","pivot":[-13.16986,17.89709,6.8143],"rotation":[0,0,32.5],"cubes":[{"origin":[-13.16986,6.89709,2.3143],"size":[0,11,9],"uv":[36,154],"mirror":true}]},{"name":"right_front","parent":"chest","pivot":[-14,60.89624,2.1857],"rotation":[-9.72039,-46.46678,-7.33019],"cubes":[{"origin":[-14,60.89624,-2.3143],"size":[0,24,9],"uv":[84,124],"mirror":true}]},{"name":"bone6","parent":"right_front","pivot":[-14,84.89624,2.1857],"rotation":[0,0,27.5],"cubes":[{"origin":[-14,35.89624,-4.3143],"size":[0,49,13],"uv":[0,156],"mirror":true}]},{"name":"right_head","parent":"bone6","pivot":[-14,35.89624,2.1857],"rotation":[0,0,32.5],"cubes":[{"origin":[-14,24.89624,-2.3143],"size":[0,11,9],"uv":[36,154],"mirror":true}]},{"name":"bone","parent":"chest","pivot":[0,61.37367,-7.46963],"rotation":[97.5,0,0],"cubes":[{"origin":[-2,59.37367,-9.46963],"size":[4,4,4],"pivot":[0,61.37367,-7.46963],"rotation":[0,45,0],"uv":[146,71]}]},{"name":"bone4","parent":"chest","pivot":[8.5,59.97959,-5.50261],"rotation":[0,57.5,0],"cubes":[{"origin":[4,50.27388,-16.81939],"size":[8,11,16],"uv":[78,11]},{"origin":[12.05,57.27388,-14.81939],"size":[0,4,9],"pivot":[12.05,59.27388,-10.31939],"rotation":[12.5,0,0],"uv":[181,28]}]},{"name":"bone2","parent":"chest","pivot":[-8.5,59.97959,-5.50261],"rotation":[0,-57.5,0],"cubes":[{"origin":[-12,50.27388,-16.81939],"size":[8,11,16],"uv":[168,0],"mirror":true},{"origin":[-12.05,57.27388,-14.81939],"size":[0,4,9],"pivot":[-12.05,59.27388,-10.31939],"rotation":[12.5,0,0],"uv":[203,93],"mirror":true}]},{"name":"left_arm","parent":"main_body","pivot":[13.5,56.10546,2.86339],"cubes":[{"origin":[14,48.89624,0.6857],"size":[3,7,6],"pivot":[4,54.89624,6.1857],"rotation":[-65,0,0],"uv":[114,153]}]},{"name":"bone3","parent":"left_arm","pivot":[16.5,55.89416,2.41023],"cubes":[{"origin":[14,49.89624,1.6857],"size":[15,4,4],"pivot":[4,54.89624,6.1857],"rotation":[-65,0,0],"uv":[126,23]}]},{"name":"hand","parent":"bone3","pivot":[29.5,55.6011,1.94304],"cubes":[{"origin":[29,47.89624,-0.3143],"size":[13,8,8],"pivot":[-2,54.89624,6.1857],"rotation":[-65,0,0],"uv":[104,111]},{"origin":[42,47.89624,-0.3143],"size":[4,8,0],"pivot":[-2,54.89624,6.1857],"rotation":[-65,0,0],"uv":[104,88]},{"origin":[42,47.89624,7.6857],"size":[4,8,0],"pivot":[-2,54.89624,6.1857],"rotation":[-65,0,0],"uv":[104,65]},{"origin":[42,55.89624,-0.3143],"size":[4,0,8],"pivot":[-2,54.89624,6.1857],"rotation":[-65,0,0],"uv":[74,16]},{"origin":[42,49.27124,2.4607],"size":[7,0,3],"pivot":[-2,54.89624,6.1857],"rotation":[-65,0,0],"uv":[131,94]},{"origin":[42,54.53555,1.6474],"size":[7,0,3],"pivot":[45.5,54.53555,0.1474],"rotation":[-25,0,0],"uv":[123,60]},{"origin":[42,54.21055,-4.3526],"size":[7,0,3],"pivot":[45.5,54.53555,0.1474],"rotation":[-102.5,0,0],"uv":[131,71]},{"origin":[42,47.89624,-0.3143],"size":[4,0,8],"pivot":[-2,54.89624,6.1857],"rotation":[-65,0,0],"uv":[74,8]}]},{"name":"right_arm","parent":"main_body","pivot":[-13.5,56.10546,2.86339],"cubes":[{"origin":[-17,48.89624,0.6857],"size":[3,7,6],"pivot":[-4,54.89624,6.1857],"rotation":[-65,0,0],"uv":[114,153],"mirror":true}]},{"name":"bone13","parent":"right_arm","pivot":[-16.5,55.89416,2.41023],"cubes":[{"origin":[-29,49.89624,1.6857],"size":[15,4,4],"pivot":[-4,54.89624,6.1857],"rotation":[-65,0,0],"uv":[126,23],"mirror":true}]},{"name":"hand2","parent":"bone13","pivot":[-29.5,55.6011,1.94304],"cubes":[{"origin":[-42,47.89624,-0.3143],"size":[13,8,8],"pivot":[2,54.89624,6.1857],"rotation":[-65,0,0],"uv":[104,111],"mirror":true},{"origin":[-46,47.89624,-0.3143],"size":[4,8,0],"pivot":[2,54.89624,6.1857],"rotation":[-65,0,0],"uv":[104,88],"mirror":true},{"origin":[-46,47.89624,7.6857],"size":[4,8,0],"pivot":[2,54.89624,6.1857],"rotation":[-65,0,0],"uv":[104,65],"mirror":true},{"origin":[-46,55.89624,-0.3143],"size":[4,0,8],"pivot":[2,54.89624,6.1857],"rotation":[-65,0,0],"uv":[74,16],"mirror":true},{"origin":[-49,49.27124,2.4607],"size":[7,0,3],"pivot":[2,54.89624,6.1857],"rotation":[-65,0,0],"uv":[131,94],"mirror":true},{"origin":[-49,54.53555,1.6474],"size":[7,0,3],"pivot":[-45.5,54.53555,0.1474],"rotation":[-25,0,0],"uv":[123,60],"mirror":true},{"origin":[-49,54.21055,-4.3526],"size":[7,0,3],"pivot":[-45.5,54.53555,0.1474],"rotation":[-102.5,0,0],"uv":[131,71],"mirror":true},{"origin":[-46,47.89624,-0.3143],"size":[4,0,8],"pivot":[2,54.89624,6.1857],"rotation":[-65,0,0],"uv":[74,8],"mirror":true}]}]}]}