{
  "species": "cobblemon:pikachu",
  "order": 9,
  "variations": [
    {
      "aspects": ["rock_star"],
      "poser": "cobblemon:pikachu",
      "model": "cobblemon:pikachu_rockstar.geo",
      "texture": "cobblemon:textures/pokemon/0025_pikachu/pikachu_cosplay_rockstar.png",
      "layers": []
    },
    {
      "aspects": ["rock_star", "shiny"],
      "model": "cobblemon:pikachu_rockstar.geo",
      "texture": "cobblemon:textures/pokemon/0025_pikachu/pikachu_cosplay_rockstar_shiny.png"
    }
  ]
}
