{
    "species": "cobblemon:unown",
    "order": 1,
    "variations": [
        {
            "aspects": [
                "character-a"
            ],
            "model": "cobblemon:unown_a.geo"
        },
        {
            "aspects": [
                "character-b"
            ],
            "model": "cobblemon:unown_b.geo"
        },
        {
            "aspects": [
                "character-c"
            ],
            "model": "cobblemon:unown_c.geo"
        },
        {
            "aspects": [
                "character-d"
            ],
            "model": "cobblemon:unown_d.geo"
        },
        {
            "aspects": [
                "character-e"
            ],
            "model": "cobblemon:unown_e.geo"
        },
        {
            "aspects": [
                "character-f"
            ],
            "model": "cobblemon:unown_f.geo"
        },
        {
            "aspects": [
                "character-g"
            ],
            "model": "cobblemon:unown_g.geo"
        },
        {
            "aspects": [
                "character-h"
            ],
            "model": "cobblemon:unown_h.geo"
        },
        {
            "aspects": [
                "character-i"
            ],
            "model": "cobblemon:unown_i.geo"
        },
        {
            "aspects": [
                "character-j"
            ],
            "model": "cobblemon:unown_j.geo"
        },
        {
            "aspects": [
                "character-k"
            ],
            "model": "cobblemon:unown_k.geo"
        },
        {
            "aspects": [
                "character-l"
            ],
            "model": "cobblemon:unown_l.geo"
        },
        {
            "aspects": [
                "character-m"
            ],
            "model": "cobblemon:unown_m.geo"
        },
        {
            "aspects": [
                "character-n"
            ],
            "model": "cobblemon:unown_n.geo"
        },
        {
            "aspects": [
                "character-o"
            ],
            "model": "cobblemon:unown_o.geo"
        },
        {
            "aspects": [
                "character-p"
            ],
            "model": "cobblemon:unown_p.geo"
        },
        {
            "aspects": [
                "character-q"
            ],
            "model": "cobblemon:unown_q.geo"
        },
        {
            "aspects": [
                "character-r"
            ],
            "model": "cobblemon:unown_r.geo"
        },
        {
            "aspects": [
                "character-s"
            ],
            "model": "cobblemon:unown_s.geo"
        },
        {
            "aspects": [
                "character-t"
            ],
            "model": "cobblemon:unown_t.geo"
        },
        {
            "aspects": [
                "character-u"
            ],
            "model": "cobblemon:unown_u.geo"
        },
        {
            "aspects": [
                "character-v"
            ],
            "model": "cobblemon:unown_v.geo"
        },
        {
            "aspects": [
                "character-w"
            ],
            "model": "cobblemon:unown_w.geo"
        },
        {
            "aspects": [
                "character-x"
            ],
            "model": "cobblemon:unown_x.geo"
        },
        {
            "aspects": [
                "character-y"
            ],
            "model": "cobblemon:unown_y.geo"
        },
        {
            "aspects": [
                "character-z"
            ],
            "model": "cobblemon:unown_z.geo"
        },
        {
            "aspects": [
                "character-!"
            ],
            "model": "cobblemon:unown_exclamation.geo",
            "texture": "cobblemon:textures/pokemon/0201_unown/unown_punctuation.png",
            "layers": [        {
                "name": "emissive",
                "texture": "cobblemon:textures/pokemon/0201_unown/unown_punctuation_emissive.png",
                "emissive": true,
                "translucent": true
            }]
        },
        {
            "aspects": [
                "character-!","shiny"
            ],
            "model": "cobblemon:unown_exclamation.geo",
            "texture": "cobblemon:textures/pokemon/0201_unown/unown_punctuation_shiny.png",
            "layers": [        {
                "name": "emissive",
                "texture": "cobblemon:textures/pokemon/0201_unown/unown_punctuation_emissive.png",
                "emissive": true,
                "translucent": true
            }]
        },
        {
            "aspects": [
                "character-?"
            ],
            "model": "cobblemon:unown_question.geo",
            "texture": "cobblemon:textures/pokemon/0201_unown/unown_punctuation.png",
            "layers": [        {
                "name": "emissive",
                "texture": "cobblemon:textures/pokemon/0201_unown/unown_punctuation_emissive.png",
                "emissive": true,
                "translucent": true
            }]
        },
        {
            "aspects": [
                "character-?","shiny"
            ],
            "model": "cobblemon:unown_question.geo",
            "texture": "cobblemon:textures/pokemon/0201_unown/unown_punctuation_shiny.png",
            "layers": [        {
                "name": "emissive",
                "texture": "cobblemon:textures/pokemon/0201_unown/unown_punctuation_emissive.png",
                "emissive": true,
                "translucent": true
            }]
        }
    ]
}